{
  "account": {
    "id": "654d40ac-0955-4865-b40b-9f03e9e0ca51",
    "cash": -36380.88,
    "portfolio_value": 100520.26,
    "buying_power": 64139.38,
    "currency": "USD",
    "account_status": "ACTIVE",
    "trading_blocked": false,
    "equity": 100520.26,
    "updated_at": "2025-08-23T05:36:15.522273"
  },
  "positions": [
    {
      "symbol": "SPY",
      "qty": 212.069,
      "market_value": 136901.14295,
      "cost_basis": 136380.84734,
      "unrealized_pl": 520.29561,
      "unrealized_plpc": 0.0038150196317735,
      "current_price": 645.55,
      "avg_entry_price": 643.096574,
      "side": "long",
      "exchange": "ARCA"
    }
  ],
  "cash": -36380.88,
  "timestamp": "2025-08-23T05:36:15.646316"
}