{
  "account": {
    "id": "654d40ac-0955-4865-b40b-9f03e9e0ca51",
    "cash": -3730.98,
    "portfolio_value": 111352.94,
    "buying_power": 107621.96,
    "currency": "USD",
    "account_status": "ACTIVE",
    "trading_blocked": false,
    "equity": 111352.94,
    "updated_at": "2026-01-12T22:50:54.235070"
  },
  "positions": [
    {
      "symbol": "CAT",
      "qty": 21.0,
      "market_value": 13104.21,
      "cost_basis": 9817.5,
      "unrealized_pl": 3286.71,
      "unrealized_plpc": 0.3347807486631016,
      "current_price": 624.01,
      "avg_entry_price": 467.5,
      "side": "long",
      "exchange": "NYSE"
    },
    {
      "symbol": "JNJ",
      "qty": 110.0,
      "market_value": 22631.95,
      "cost_basis": 19515.65,
      "unrealized_pl": 3116.3,
      "unrealized_plpc": 0.1596821012879407,
      "current_price": 205.745,
      "avg_entry_price": 177.415,
      "side": "long",
      "exchange": "NYSE"
    },
    {
      "symbol": "MSFT",
      "qty": 4.0,
      "market_value": 1922.16,
      "cost_basis": 2006.28,
      "unrealized_pl": -84.12,
      "unrealized_plpc": -0.0419283449967103,
      "current_price": 480.54,
      "avg_entry_price": 501.57,
      "side": "long",
      "exchange": "NASDAQ"
    },
    {
      "symbol": "NVDA",
      "qty": 121.0,
      "market_value": 22385.2178,
      "cost_basis": 21329.99,
      "unrealized_pl": 1055.2278,
      "unrealized_plpc": 0.0494715562454553,
      "current_price": 185.0018,
      "avg_entry_price": 176.280909,
      "side": "long",
      "exchange": "NASDAQ"
    },
    {
      "symbol": "SPY",
      "qty": 47.069,
      "market_value": 32634.585115,
      "cost_basis": 30269.912639,
      "unrealized_pl": 2364.672476,
      "unrealized_plpc": 0.0781195672482165,
      "current_price": 693.335,
      "avg_entry_price": 643.096574,
      "side": "long",
      "exchange": "ARCA"
    },
    {
      "symbol": "XLF",
      "qty": 200.0,
      "market_value": 11019.0,
      "cost_basis": 10546.07,
      "unrealized_pl": 472.93,
      "unrealized_plpc": 0.0448441931449346,
      "current_price": 55.095,
      "avg_entry_price": 52.73035,
      "side": "long",
      "exchange": "ARCA"
    },
    {
      "symbol": "XLP",
      "qty": 12.0,
      "market_value": 959.16,
      "cost_basis": 963.97,
      "unrealized_pl": -4.81,
      "unrealized_plpc": -0.0049897818396838,
      "current_price": 79.93,
      "avg_entry_price": 80.330833,
      "side": "long",
      "exchange": "ARCA"
    },
    {
      "symbol": "XOM",
      "qty": 85.0,
      "market_value": 10426.95,
      "cost_basis": 9797.86,
      "unrealized_pl": 629.09,
      "unrealized_plpc": 0.0642068778284238,
      "current_price": 122.67,
      "avg_entry_price": 115.268941,
      "side": "long",
      "exchange": "NYSE"
    }
  ],
  "cash": -3730.98,
  "timestamp": "2026-01-12T22:50:54.262390"
}