{
  "account": {
    "id": "654d40ac-0955-4865-b40b-9f03e9e0ca51",
    "cash": -3730.98,
    "portfolio_value": 106356.44,
    "buying_power": 102625.46,
    "currency": "USD",
    "account_status": "ACTIVE",
    "trading_blocked": false,
    "equity": 106356.44,
    "updated_at": "2025-11-19T21:43:02.428266"
  },
  "positions": [
    {
      "symbol": "CAT",
      "qty": 21.0,
      "market_value": 11509.68,
      "cost_basis": 9817.5,
      "unrealized_pl": 1692.18,
      "unrealized_plpc": 0.1723636363636364,
      "current_price": 548.08,
      "avg_entry_price": 467.5,
      "side": "long",
      "exchange": "NYSE"
    },
    {
      "symbol": "JNJ",
      "qty": 110.0,
      "market_value": 21945.0,
      "cost_basis": 19515.65,
      "unrealized_pl": 2429.35,
      "unrealized_plpc": 0.1244821463799566,
      "current_price": 199.5,
      "avg_entry_price": 177.415,
      "side": "long",
      "exchange": "NYSE"
    },
    {
      "symbol": "MSFT",
      "qty": 4.0,
      "market_value": 1970.4,
      "cost_basis": 2006.28,
      "unrealized_pl": -35.88,
      "unrealized_plpc": -0.0178838447275555,
      "current_price": 492.6,
      "avg_entry_price": 501.57,
      "side": "long",
      "exchange": "NASDAQ"
    },
    {
      "symbol": "NVDA",
      "qty": 121.0,
      "market_value": 22322.08,
      "cost_basis": 21329.99,
      "unrealized_pl": 992.09,
      "unrealized_plpc": 0.0465115079753905,
      "current_price": 184.48,
      "avg_entry_price": 176.280909,
      "side": "long",
      "exchange": "NASDAQ"
    },
    {
      "symbol": "SPY",
      "qty": 47.069,
      "market_value": 31156.38317,
      "cost_basis": 30269.912639,
      "unrealized_pl": 886.470531,
      "unrealized_plpc": 0.0292855331818125,
      "current_price": 661.93,
      "avg_entry_price": 643.096574,
      "side": "long",
      "exchange": "ARCA"
    },
    {
      "symbol": "XLF",
      "qty": 200.0,
      "market_value": 10290.0,
      "cost_basis": 10546.07,
      "unrealized_pl": -256.07,
      "unrealized_plpc": -0.0242810829057649,
      "current_price": 51.45,
      "avg_entry_price": 52.73035,
      "side": "long",
      "exchange": "ARCA"
    },
    {
      "symbol": "XLP",
      "qty": 12.0,
      "market_value": 925.08,
      "cost_basis": 963.97,
      "unrealized_pl": -38.89,
      "unrealized_plpc": -0.0403435791570277,
      "current_price": 77.09,
      "avg_entry_price": 80.330833,
      "side": "long",
      "exchange": "ARCA"
    },
    {
      "symbol": "XOM",
      "qty": 85.0,
      "market_value": 9968.8,
      "cost_basis": 9797.86,
      "unrealized_pl": 170.94,
      "unrealized_plpc": 0.0174466669252265,
      "current_price": 117.28,
      "avg_entry_price": 115.268941,
      "side": "long",
      "exchange": "NYSE"
    }
  ],
  "cash": -3730.98,
  "timestamp": "2025-11-19T21:43:02.436697"
}