{
  "account": {
    "id": "654d40ac-0955-4865-b40b-9f03e9e0ca51",
    "cash": -3730.98,
    "portfolio_value": 119692.59,
    "buying_power": 115961.61,
    "currency": "USD",
    "account_status": "ACTIVE",
    "trading_blocked": false,
    "equity": 119692.59,
    "updated_at": "2026-02-13T17:59:50.610937"
  },
  "positions": [
    {
      "symbol": "CAT",
      "qty": 21.0,
      "market_value": 16000.74,
      "cost_basis": 9817.5,
      "unrealized_pl": 6183.24,
      "unrealized_plpc": 0.62982,
      "current_price": 761.94,
      "avg_entry_price": 467.5,
      "side": "long",
      "exchange": "NYSE"
    },
    {
      "symbol": "JNJ",
      "qty": 110.0,
      "market_value": 26900.5,
      "cost_basis": 19515.65,
      "unrealized_pl": 7384.85,
      "unrealized_plpc": 0.37841,
      "current_price": 244.55,
      "avg_entry_price": 177.415,
      "side": "long",
      "exchange": "NYSE"
    },
    {
      "symbol": "MSFT",
      "qty": 4.0,
      "market_value": 1605.2,
      "cost_basis": 2006.28,
      "unrealized_pl": -401.08,
      "unrealized_plpc": -0.19991,
      "current_price": 401.3,
      "avg_entry_price": 501.57,
      "side": "long",
      "exchange": "NASDAQ"
    },
    {
      "symbol": "NVDA",
      "qty": 121.0,
      "market_value": 22702.02,
      "cost_basis": 21329.989989,
      "unrealized_pl": 1372.030011,
      "unrealized_plpc": 0.06432,
      "current_price": 187.62,
      "avg_entry_price": 176.280909,
      "side": "long",
      "exchange": "NASDAQ"
    },
    {
      "symbol": "SPY",
      "qty": 47.069,
      "market_value": 32061.99073,
      "cost_basis": 30269.912642,
      "unrealized_pl": 1792.078088,
      "unrealized_plpc": 0.0592,
      "current_price": 681.17,
      "avg_entry_price": 643.096574,
      "side": "long",
      "exchange": "ARCA"
    },
    {
      "symbol": "XLF",
      "qty": 200.0,
      "market_value": 10336.0,
      "cost_basis": 10546.07,
      "unrealized_pl": -210.07,
      "unrealized_plpc": -0.01992,
      "current_price": 51.68,
      "avg_entry_price": 52.73035,
      "side": "long",
      "exchange": "ARCA"
    },
    {
      "symbol": "XLP",
      "qty": 12.0,
      "market_value": 1070.52,
      "cost_basis": 963.969996,
      "unrealized_pl": 106.550004,
      "unrealized_plpc": 0.11053,
      "current_price": 89.21,
      "avg_entry_price": 80.330833,
      "side": "long",
      "exchange": "ARCA"
    },
    {
      "symbol": "XOM",
      "qty": 85.0,
      "market_value": 12746.6,
      "cost_basis": 9797.859985,
      "unrealized_pl": 2948.740015,
      "unrealized_plpc": 0.30096,
      "current_price": 149.96,
      "avg_entry_price": 115.268941,
      "side": "long",
      "exchange": "NYSE"
    }
  ],
  "cash": -3730.98,
  "timestamp": "2026-02-13T17:59:50.636177"
}