{
  "account": {
    "id": "654d40ac-0955-4865-b40b-9f03e9e0ca51",
    "cash": -3730.98,
    "portfolio_value": 124935.15,
    "buying_power": 121204.17,
    "currency": "USD",
    "account_status": "ACTIVE",
    "trading_blocked": false,
    "equity": 124935.15,
    "updated_at": "2026-05-08T07:33:41.966199"
  },
  "positions": [
    {
      "symbol": "CAT",
      "qty": 21.0,
      "market_value": 18774.0,
      "cost_basis": 9817.5,
      "unrealized_pl": 8956.5,
      "unrealized_plpc": 0.9123,
      "current_price": 894.0,
      "avg_entry_price": 467.5,
      "side": "long",
      "exchange": "NYSE"
    },
    {
      "symbol": "JNJ",
      "qty": 110.0,
      "market_value": 24475.0,
      "cost_basis": 19515.65,
      "unrealized_pl": 4959.35,
      "unrealized_plpc": 0.25412,
      "current_price": 222.5,
      "avg_entry_price": 177.415,
      "side": "long",
      "exchange": "NYSE"
    },
    {
      "symbol": "MSFT",
      "qty": 4.0,
      "market_value": 1677.11,
      "cost_basis": 2006.28,
      "unrealized_pl": -329.17,
      "unrealized_plpc": -0.16407,
      "current_price": 419.2775,
      "avg_entry_price": 501.57,
      "side": "long",
      "exchange": "NASDAQ"
    },
    {
      "symbol": "NVDA",
      "qty": 121.0,
      "market_value": 25507.6349,
      "cost_basis": 21329.989989,
      "unrealized_pl": 4177.644911,
      "unrealized_plpc": 0.19586,
      "current_price": 210.8069,
      "avg_entry_price": 176.280909,
      "side": "long",
      "exchange": "NASDAQ"
    },
    {
      "symbol": "SPY",
      "qty": 47.069,
      "market_value": 34387.19933,
      "cost_basis": 30269.912642,
      "unrealized_pl": 4117.286688,
      "unrealized_plpc": 0.13602,
      "current_price": 730.57,
      "avg_entry_price": 643.096574,
      "side": "long",
      "exchange": "ARCA"
    },
    {
      "symbol": "XLF",
      "qty": 200.0,
      "market_value": 10302.0,
      "cost_basis": 10546.07,
      "unrealized_pl": -244.07,
      "unrealized_plpc": -0.02314,
      "current_price": 51.51,
      "avg_entry_price": 52.73035,
      "side": "long",
      "exchange": "ARCA"
    },
    {
      "symbol": "XLP",
      "qty": 12.0,
      "market_value": 1008.24,
      "cost_basis": 963.969996,
      "unrealized_pl": 44.270004,
      "unrealized_plpc": 0.04592,
      "current_price": 84.02,
      "avg_entry_price": 80.330833,
      "side": "long",
      "exchange": "ARCA"
    },
    {
      "symbol": "XOM",
      "qty": 85.0,
      "market_value": 12534.95,
      "cost_basis": 9797.859985,
      "unrealized_pl": 2737.090015,
      "unrealized_plpc": 0.27936,
      "current_price": 147.47,
      "avg_entry_price": 115.268941,
      "side": "long",
      "exchange": "NYSE"
    }
  ],
  "cash": -3730.98,
  "timestamp": "2026-05-08T07:33:42.008243"
}