{
  "account": {
    "id": "654d40ac-0955-4865-b40b-9f03e9e0ca51",
    "cash": -3730.98,
    "portfolio_value": 108073.79,
    "buying_power": 104342.81,
    "currency": "USD",
    "account_status": "ACTIVE",
    "trading_blocked": false,
    "equity": 108073.79,
    "updated_at": "2025-12-03T22:54:50.715426"
  },
  "positions": [
    {
      "symbol": "CAT",
      "qty": 21.0,
      "market_value": 11909.94,
      "cost_basis": 9817.5,
      "unrealized_pl": 2092.44,
      "unrealized_plpc": 0.2131336898395722,
      "current_price": 567.14,
      "avg_entry_price": 467.5,
      "side": "long",
      "exchange": "NYSE"
    },
    {
      "symbol": "JNJ",
      "qty": 110.0,
      "market_value": 22674.3,
      "cost_basis": 19515.65,
      "unrealized_pl": 3158.65,
      "unrealized_plpc": 0.1618521545528845,
      "current_price": 206.13,
      "avg_entry_price": 177.415,
      "side": "long",
      "exchange": "NYSE"
    },
    {
      "symbol": "MSFT",
      "qty": 4.0,
      "market_value": 1906.6,
      "cost_basis": 2006.28,
      "unrealized_pl": -99.68,
      "unrealized_plpc": -0.0496839922642901,
      "current_price": 476.65,
      "avg_entry_price": 501.57,
      "side": "long",
      "exchange": "NASDAQ"
    },
    {
      "symbol": "NVDA",
      "qty": 121.0,
      "market_value": 21749.75,
      "cost_basis": 21329.99,
      "unrealized_pl": 419.76,
      "unrealized_plpc": 0.0196793341206442,
      "current_price": 179.75,
      "avg_entry_price": 176.280909,
      "side": "long",
      "exchange": "NASDAQ"
    },
    {
      "symbol": "SPY",
      "qty": 47.069,
      "market_value": 32037.04416,
      "cost_basis": 30269.912639,
      "unrealized_pl": 1767.131521,
      "unrealized_plpc": 0.0583791417595046,
      "current_price": 680.64,
      "avg_entry_price": 643.096574,
      "side": "long",
      "exchange": "ARCA"
    },
    {
      "symbol": "XLF",
      "qty": 200.0,
      "market_value": 10628.0,
      "cost_basis": 10546.07,
      "unrealized_pl": 81.93,
      "unrealized_plpc": 0.0077687707363975,
      "current_price": 53.14,
      "avg_entry_price": 52.73035,
      "side": "long",
      "exchange": "ARCA"
    },
    {
      "symbol": "XLP",
      "qty": 12.0,
      "market_value": 949.56,
      "cost_basis": 963.97,
      "unrealized_pl": -14.41,
      "unrealized_plpc": -0.0149485979854145,
      "current_price": 79.13,
      "avg_entry_price": 80.330833,
      "side": "long",
      "exchange": "ARCA"
    },
    {
      "symbol": "XOM",
      "qty": 85.0,
      "market_value": 9945.0,
      "cost_basis": 9797.86,
      "unrealized_pl": 147.14,
      "unrealized_plpc": 0.0150175650601254,
      "current_price": 117.0,
      "avg_entry_price": 115.268941,
      "side": "long",
      "exchange": "NYSE"
    }
  ],
  "cash": -3730.98,
  "timestamp": "2025-12-03T22:54:50.780366"
}