{
  "account": {
    "id": "654d40ac-0955-4865-b40b-9f03e9e0ca51",
    "cash": -3730.98,
    "portfolio_value": 124917.74,
    "buying_power": 121186.76,
    "currency": "USD",
    "account_status": "ACTIVE",
    "trading_blocked": false,
    "equity": 124917.74,
    "updated_at": "2026-05-01T19:51:19.167484"
  },
  "positions": [
    {
      "symbol": "CAT",
      "qty": 21.0,
      "market_value": 18763.5,
      "cost_basis": 9817.5,
      "unrealized_pl": 8946.0,
      "unrealized_plpc": 0.91123,
      "current_price": 893.5,
      "avg_entry_price": 467.5,
      "side": "long",
      "exchange": "NYSE"
    },
    {
      "symbol": "JNJ",
      "qty": 110.0,
      "market_value": 25304.4,
      "cost_basis": 19515.65,
      "unrealized_pl": 5788.75,
      "unrealized_plpc": 0.29662,
      "current_price": 230.04,
      "avg_entry_price": 177.415,
      "side": "long",
      "exchange": "NYSE"
    },
    {
      "symbol": "MSFT",
      "qty": 4.0,
      "market_value": 1637.118,
      "cost_basis": 2006.28,
      "unrealized_pl": -369.162,
      "unrealized_plpc": -0.184,
      "current_price": 409.2795,
      "avg_entry_price": 501.57,
      "side": "long",
      "exchange": "NASDAQ"
    },
    {
      "symbol": "NVDA",
      "qty": 121.0,
      "market_value": 24353.67,
      "cost_basis": 21329.989989,
      "unrealized_pl": 3023.680011,
      "unrealized_plpc": 0.14176,
      "current_price": 201.27,
      "avg_entry_price": 176.280909,
      "side": "long",
      "exchange": "NASDAQ"
    },
    {
      "symbol": "SPY",
      "qty": 47.069,
      "market_value": 33902.906389,
      "cost_basis": 30269.912642,
      "unrealized_pl": 3632.993747,
      "unrealized_plpc": 0.12002,
      "current_price": 720.281,
      "avg_entry_price": 643.096574,
      "side": "long",
      "exchange": "ARCA"
    },
    {
      "symbol": "XLF",
      "qty": 200.0,
      "market_value": 10454.3,
      "cost_basis": 10546.07,
      "unrealized_pl": -91.77,
      "unrealized_plpc": -0.0087,
      "current_price": 52.2715,
      "avg_entry_price": 52.73035,
      "side": "long",
      "exchange": "ARCA"
    },
    {
      "symbol": "XLP",
      "qty": 12.0,
      "market_value": 1014.48,
      "cost_basis": 963.969996,
      "unrealized_pl": 50.510004,
      "unrealized_plpc": 0.0524,
      "current_price": 84.54,
      "avg_entry_price": 80.330833,
      "side": "long",
      "exchange": "ARCA"
    },
    {
      "symbol": "XOM",
      "qty": 85.0,
      "market_value": 13218.35,
      "cost_basis": 9797.859985,
      "unrealized_pl": 3420.490015,
      "unrealized_plpc": 0.34911,
      "current_price": 155.51,
      "avg_entry_price": 115.268941,
      "side": "long",
      "exchange": "NYSE"
    }
  ],
  "cash": -3730.98,
  "timestamp": "2026-05-01T19:51:19.195599"
}