{
  "account": {
    "id": "654d40ac-0955-4865-b40b-9f03e9e0ca51",
    "cash": -3730.98,
    "portfolio_value": 118898.79,
    "buying_power": 115167.81,
    "currency": "USD",
    "account_status": "ACTIVE",
    "trading_blocked": false,
    "equity": 118898.79,
    "updated_at": "2026-02-18T00:38:15.374560"
  },
  "positions": [
    {
      "symbol": "CAT",
      "qty": 21.0,
      "market_value": 16048.305,
      "cost_basis": 9817.5,
      "unrealized_pl": 6230.805,
      "unrealized_plpc": 0.63466,
      "current_price": 764.205,
      "avg_entry_price": 467.5,
      "side": "long",
      "exchange": "NYSE"
    },
    {
      "symbol": "JNJ",
      "qty": 110.0,
      "market_value": 26644.2,
      "cost_basis": 19515.65,
      "unrealized_pl": 7128.55,
      "unrealized_plpc": 0.36527,
      "current_price": 242.22,
      "avg_entry_price": 177.415,
      "side": "long",
      "exchange": "NYSE"
    },
    {
      "symbol": "MSFT",
      "qty": 4.0,
      "market_value": 1596.92,
      "cost_basis": 2006.28,
      "unrealized_pl": -409.36,
      "unrealized_plpc": -0.20404,
      "current_price": 399.23,
      "avg_entry_price": 501.57,
      "side": "long",
      "exchange": "NASDAQ"
    },
    {
      "symbol": "NVDA",
      "qty": 121.0,
      "market_value": 22293.3909,
      "cost_basis": 21329.989989,
      "unrealized_pl": 963.400911,
      "unrealized_plpc": 0.04517,
      "current_price": 184.2429,
      "avg_entry_price": 176.280909,
      "side": "long",
      "exchange": "NASDAQ"
    },
    {
      "symbol": "SPY",
      "qty": 47.069,
      "market_value": 32119.650255,
      "cost_basis": 30269.912642,
      "unrealized_pl": 1849.737613,
      "unrealized_plpc": 0.06111,
      "current_price": 682.395,
      "avg_entry_price": 643.096574,
      "side": "long",
      "exchange": "ARCA"
    },
    {
      "symbol": "XLF",
      "qty": 200.0,
      "market_value": 10461.0,
      "cost_basis": 10546.07,
      "unrealized_pl": -85.07,
      "unrealized_plpc": -0.00807,
      "current_price": 52.305,
      "avg_entry_price": 52.73035,
      "side": "long",
      "exchange": "ARCA"
    },
    {
      "symbol": "XLP",
      "qty": 12.0,
      "market_value": 1056.3,
      "cost_basis": 963.969996,
      "unrealized_pl": 92.330004,
      "unrealized_plpc": 0.09578,
      "current_price": 88.025,
      "avg_entry_price": 80.330833,
      "side": "long",
      "exchange": "ARCA"
    },
    {
      "symbol": "XOM",
      "qty": 85.0,
      "market_value": 12410.0,
      "cost_basis": 9797.859985,
      "unrealized_pl": 2612.140015,
      "unrealized_plpc": 0.2666,
      "current_price": 146.0,
      "avg_entry_price": 115.268941,
      "side": "long",
      "exchange": "NYSE"
    }
  ],
  "cash": -3730.98,
  "timestamp": "2026-02-18T00:38:15.408685"
}