{
  "account": {
    "id": "654d40ac-0955-4865-b40b-9f03e9e0ca51",
    "cash": -4300.16,
    "portfolio_value": 109069.91,
    "buying_power": 104769.75,
    "currency": "USD",
    "account_status": "ACTIVE",
    "trading_blocked": false,
    "equity": 109069.91,
    "updated_at": "2025-11-01T02:17:21.322149"
  },
  "positions": [
    {
      "symbol": "CAT",
      "qty": 22.0,
      "market_value": 12703.9,
      "cost_basis": 10285.0,
      "unrealized_pl": 2418.9,
      "unrealized_plpc": 0.2351871657754011,
      "current_price": 577.45,
      "avg_entry_price": 467.5,
      "side": "long",
      "exchange": "NYSE"
    },
    {
      "symbol": "JNJ",
      "qty": 110.0,
      "market_value": 20728.4,
      "cost_basis": 19515.65,
      "unrealized_pl": 1212.75,
      "unrealized_plpc": 0.0621424344052081,
      "current_price": 188.44,
      "avg_entry_price": 177.415,
      "side": "long",
      "exchange": "NYSE"
    },
    {
      "symbol": "MSFT",
      "qty": 4.0,
      "market_value": 2070.12,
      "cost_basis": 2006.28,
      "unrealized_pl": 63.84,
      "unrealized_plpc": 0.0318200849333094,
      "current_price": 517.53,
      "avg_entry_price": 501.57,
      "side": "long",
      "exchange": "NASDAQ"
    },
    {
      "symbol": "NVDA",
      "qty": 121.0,
      "market_value": 24651.33,
      "cost_basis": 21329.99,
      "unrealized_pl": 3321.34,
      "unrealized_plpc": 0.1557122155237766,
      "current_price": 203.73,
      "avg_entry_price": 176.280909,
      "side": "long",
      "exchange": "NASDAQ"
    },
    {
      "symbol": "SPY",
      "qty": 47.069,
      "market_value": 32088.114025,
      "cost_basis": 30269.912639,
      "unrealized_pl": 1818.201386,
      "unrealized_plpc": 0.0600662911612574,
      "current_price": 681.725,
      "avg_entry_price": 643.096574,
      "side": "long",
      "exchange": "ARCA"
    },
    {
      "symbol": "XLF",
      "qty": 200.0,
      "market_value": 10449.0,
      "cost_basis": 10546.07,
      "unrealized_pl": -97.07,
      "unrealized_plpc": -0.0092043766066411,
      "current_price": 52.245,
      "avg_entry_price": 52.73035,
      "side": "long",
      "exchange": "ARCA"
    },
    {
      "symbol": "XLP",
      "qty": 12.0,
      "market_value": 913.56,
      "cost_basis": 963.97,
      "unrealized_pl": -50.41,
      "unrealized_plpc": -0.0522941585319045,
      "current_price": 76.13,
      "avg_entry_price": 80.330833,
      "side": "long",
      "exchange": "ARCA"
    },
    {
      "symbol": "XOM",
      "qty": 85.0,
      "market_value": 9765.65,
      "cost_basis": 9797.86,
      "unrealized_pl": -32.21,
      "unrealized_plpc": -0.0032874525661726,
      "current_price": 114.89,
      "avg_entry_price": 115.268941,
      "side": "long",
      "exchange": "NYSE"
    }
  ],
  "cash": -4300.16,
  "timestamp": "2025-11-01T02:17:21.335282"
}