{
  "account": {
    "id": "654d40ac-0955-4865-b40b-9f03e9e0ca51",
    "cash": -3730.98,
    "portfolio_value": 130613.88,
    "buying_power": 361241.69,
    "currency": "USD",
    "account_status": "ACTIVE",
    "trading_blocked": false,
    "equity": 130613.88,
    "updated_at": "2026-07-23T06:31:15.499311"
  },
  "positions": [
    {
      "symbol": "CAT",
      "qty": 21.0,
      "market_value": 18675.51,
      "cost_basis": 9817.5,
      "unrealized_pl": 8858.01,
      "unrealized_plpc": 0.90227,
      "current_price": 889.31,
      "avg_entry_price": 467.5,
      "side": "long",
      "exchange": "NYSE"
    },
    {
      "symbol": "JNJ",
      "qty": 110.0,
      "market_value": 28119.3,
      "cost_basis": 19515.65,
      "unrealized_pl": 8603.65,
      "unrealized_plpc": 0.44086,
      "current_price": 255.63,
      "avg_entry_price": 177.415,
      "side": "long",
      "exchange": "NYSE"
    },
    {
      "symbol": "MSFT",
      "qty": 4.0,
      "market_value": 1550.6,
      "cost_basis": 2006.28,
      "unrealized_pl": -455.68,
      "unrealized_plpc": -0.22713,
      "current_price": 387.65,
      "avg_entry_price": 501.57,
      "side": "long",
      "exchange": "NASDAQ"
    },
    {
      "symbol": "NVDA",
      "qty": 121.0,
      "market_value": 25537.05,
      "cost_basis": 21329.989989,
      "unrealized_pl": 4207.060011,
      "unrealized_plpc": 0.19724,
      "current_price": 211.05,
      "avg_entry_price": 176.280909,
      "side": "long",
      "exchange": "NASDAQ"
    },
    {
      "symbol": "SPY",
      "qty": 47.069,
      "market_value": 35111.59124,
      "cost_basis": 30269.912642,
      "unrealized_pl": 4841.678598,
      "unrealized_plpc": 0.15995,
      "current_price": 745.96,
      "avg_entry_price": 643.096574,
      "side": "long",
      "exchange": "ARCA"
    },
    {
      "symbol": "XLF",
      "qty": 200.0,
      "market_value": 11210.0,
      "cost_basis": 10546.07,
      "unrealized_pl": 663.93,
      "unrealized_plpc": 0.06296,
      "current_price": 56.05,
      "avg_entry_price": 52.73035,
      "side": "long",
      "exchange": "ARCA"
    },
    {
      "symbol": "XLP",
      "qty": 12.0,
      "market_value": 1012.56,
      "cost_basis": 963.969996,
      "unrealized_pl": 48.590004,
      "unrealized_plpc": 0.05041,
      "current_price": 84.38,
      "avg_entry_price": 80.330833,
      "side": "long",
      "exchange": "ARCA"
    },
    {
      "symbol": "XOM",
      "qty": 85.0,
      "market_value": 13128.25,
      "cost_basis": 9797.95,
      "unrealized_pl": 3330.3,
      "unrealized_plpc": 0.3399,
      "current_price": 154.45,
      "avg_entry_price": 115.27,
      "side": "long",
      "exchange": "NYSE"
    }
  ],
  "cash": -3730.98,
  "timestamp": "2026-07-23T06:31:15.565360"
}