{
  "account": {
    "id": "654d40ac-0955-4865-b40b-9f03e9e0ca51",
    "cash": 6245.92,
    "portfolio_value": 104856.17,
    "buying_power": 111102.09,
    "currency": "USD",
    "account_status": "ACTIVE",
    "trading_blocked": false,
    "equity": 104856.17,
    "updated_at": "2025-10-10T23:29:28.859271"
  },
  "positions": [
    {
      "symbol": "CAT",
      "qty": 22.0,
      "market_value": 10971.84,
      "cost_basis": 10285.0,
      "unrealized_pl": 686.84,
      "unrealized_plpc": 0.0667807486631016,
      "current_price": 498.72,
      "avg_entry_price": 467.5,
      "side": "long",
      "exchange": "NYSE"
    },
    {
      "symbol": "JNJ",
      "qty": 110.0,
      "market_value": 21030.9,
      "cost_basis": 19515.65,
      "unrealized_pl": 1515.25,
      "unrealized_plpc": 0.0776428148690922,
      "current_price": 191.19,
      "avg_entry_price": 177.415,
      "side": "long",
      "exchange": "NYSE"
    },
    {
      "symbol": "MSFT",
      "qty": 4.0,
      "market_value": 2065.84,
      "cost_basis": 2006.28,
      "unrealized_pl": 59.56,
      "unrealized_plpc": 0.0296867834998106,
      "current_price": 516.46,
      "avg_entry_price": 501.57,
      "side": "long",
      "exchange": "NASDAQ"
    },
    {
      "symbol": "NVDA",
      "qty": 121.0,
      "market_value": 22882.9392,
      "cost_basis": 21329.99,
      "unrealized_pl": 1552.9492,
      "unrealized_plpc": 0.0728059038002362,
      "current_price": 189.1152,
      "avg_entry_price": 176.280909,
      "side": "long",
      "exchange": "NASDAQ"
    },
    {
      "symbol": "SPY",
      "qty": 47.069,
      "market_value": 31191.21423,
      "cost_basis": 30269.912639,
      "unrealized_pl": 921.301591,
      "unrealized_plpc": 0.0304362157231002,
      "current_price": 662.67,
      "avg_entry_price": 643.096574,
      "side": "long",
      "exchange": "ARCA"
    },
    {
      "symbol": "XLP",
      "qty": 12.0,
      "market_value": 941.1,
      "cost_basis": 963.97,
      "unrealized_pl": -22.87,
      "unrealized_plpc": -0.0237248047138396,
      "current_price": 78.425,
      "avg_entry_price": 80.330833,
      "side": "long",
      "exchange": "ARCA"
    },
    {
      "symbol": "XOM",
      "qty": 85.0,
      "market_value": 9525.95,
      "cost_basis": 9797.86,
      "unrealized_pl": -271.91,
      "unrealized_plpc": -0.0277519784932628,
      "current_price": 112.07,
      "avg_entry_price": 115.268941,
      "side": "long",
      "exchange": "NYSE"
    }
  ],
  "cash": 6245.92,
  "timestamp": "2025-10-10T23:29:28.881899"
}