{
  "account": {
    "id": "654d40ac-0955-4865-b40b-9f03e9e0ca51",
    "cash": -4300.16,
    "portfolio_value": 107532.1,
    "buying_power": 103231.94,
    "currency": "USD",
    "account_status": "ACTIVE",
    "trading_blocked": false,
    "equity": 107532.1,
    "updated_at": "2025-11-10T20:23:11.825206"
  },
  "positions": [
    {
      "symbol": "CAT",
      "qty": 22.0,
      "market_value": 12546.6,
      "cost_basis": 10285.0,
      "unrealized_pl": 2261.6,
      "unrealized_plpc": 0.2198930481283422,
      "current_price": 570.3,
      "avg_entry_price": 467.5,
      "side": "long",
      "exchange": "NYSE"
    },
    {
      "symbol": "JNJ",
      "qty": 110.0,
      "market_value": 20456.7,
      "cost_basis": 19515.65,
      "unrealized_pl": 941.05,
      "unrealized_plpc": 0.0482202744976468,
      "current_price": 185.97,
      "avg_entry_price": 177.415,
      "side": "long",
      "exchange": "NYSE"
    },
    {
      "symbol": "MSFT",
      "qty": 4.0,
      "market_value": 2003.48,
      "cost_basis": 2006.28,
      "unrealized_pl": -2.8,
      "unrealized_plpc": -0.0013956177602329,
      "current_price": 500.87,
      "avg_entry_price": 501.57,
      "side": "long",
      "exchange": "NASDAQ"
    },
    {
      "symbol": "NVDA",
      "qty": 121.0,
      "market_value": 23462.021,
      "cost_basis": 21329.99,
      "unrealized_pl": 2132.031,
      "unrealized_plpc": 0.0999546178877721,
      "current_price": 193.901,
      "avg_entry_price": 176.280909,
      "side": "long",
      "exchange": "NASDAQ"
    },
    {
      "symbol": "SPY",
      "qty": 47.069,
      "market_value": 31870.89059,
      "cost_basis": 30269.912639,
      "unrealized_pl": 1600.977951,
      "unrealized_plpc": 0.052890075042281,
      "current_price": 677.11,
      "avg_entry_price": 643.096574,
      "side": "long",
      "exchange": "ARCA"
    },
    {
      "symbol": "XLF",
      "qty": 200.0,
      "market_value": 10590.0,
      "cost_basis": 10546.07,
      "unrealized_pl": 43.93,
      "unrealized_plpc": 0.0041655327529592,
      "current_price": 52.95,
      "avg_entry_price": 52.73035,
      "side": "long",
      "exchange": "ARCA"
    },
    {
      "symbol": "XLP",
      "qty": 12.0,
      "market_value": 919.32,
      "cost_basis": 963.97,
      "unrealized_pl": -44.65,
      "unrealized_plpc": -0.0463188688444661,
      "current_price": 76.61,
      "avg_entry_price": 80.330833,
      "side": "long",
      "exchange": "ARCA"
    },
    {
      "symbol": "XOM",
      "qty": 85.0,
      "market_value": 9983.25,
      "cost_basis": 9797.86,
      "unrealized_pl": 185.39,
      "unrealized_plpc": 0.0189214787718951,
      "current_price": 117.45,
      "avg_entry_price": 115.268941,
      "side": "long",
      "exchange": "NYSE"
    }
  ],
  "cash": -4300.16,
  "timestamp": "2025-11-10T20:23:11.881418"
}