{
  "account": {
    "id": "654d40ac-0955-4865-b40b-9f03e9e0ca51",
    "cash": -3730.98,
    "portfolio_value": 108085.74,
    "buying_power": 104354.76,
    "currency": "USD",
    "account_status": "ACTIVE",
    "trading_blocked": false,
    "equity": 108085.74,
    "updated_at": "2025-12-02T00:17:04.492522"
  },
  "positions": [
    {
      "symbol": "CAT",
      "qty": 21.0,
      "market_value": 12020.6898,
      "cost_basis": 9817.5,
      "unrealized_pl": 2203.1898,
      "unrealized_plpc": 0.2244145454545455,
      "current_price": 572.4138,
      "avg_entry_price": 467.5,
      "side": "long",
      "exchange": "NYSE"
    },
    {
      "symbol": "JNJ",
      "qty": 110.0,
      "market_value": 22731.5,
      "cost_basis": 19515.65,
      "unrealized_pl": 3215.85,
      "unrealized_plpc": 0.1647831355860553,
      "current_price": 206.65,
      "avg_entry_price": 177.415,
      "side": "long",
      "exchange": "NYSE"
    },
    {
      "symbol": "MSFT",
      "qty": 4.0,
      "market_value": 1949.9776,
      "cost_basis": 2006.28,
      "unrealized_pl": -56.3024,
      "unrealized_plpc": -0.0280630819227625,
      "current_price": 487.4944,
      "avg_entry_price": 501.57,
      "side": "long",
      "exchange": "NASDAQ"
    },
    {
      "symbol": "NVDA",
      "qty": 121.0,
      "market_value": 21588.82,
      "cost_basis": 21329.99,
      "unrealized_pl": 258.83,
      "unrealized_plpc": 0.0121345579627557,
      "current_price": 178.42,
      "avg_entry_price": 176.280909,
      "side": "long",
      "exchange": "NASDAQ"
    },
    {
      "symbol": "SPY",
      "qty": 47.069,
      "market_value": 32014.45104,
      "cost_basis": 30269.912639,
      "unrealized_pl": 1744.538401,
      "unrealized_plpc": 0.0576327530840747,
      "current_price": 680.16,
      "avg_entry_price": 643.096574,
      "side": "long",
      "exchange": "ARCA"
    },
    {
      "symbol": "XLF",
      "qty": 200.0,
      "market_value": 10632.0,
      "cost_basis": 10546.07,
      "unrealized_pl": 85.93,
      "unrealized_plpc": 0.0081480589451805,
      "current_price": 53.16,
      "avg_entry_price": 52.73035,
      "side": "long",
      "exchange": "ARCA"
    },
    {
      "symbol": "XLP",
      "qty": 12.0,
      "market_value": 952.56,
      "cost_basis": 963.97,
      "unrealized_pl": -11.41,
      "unrealized_plpc": -0.0118364679398736,
      "current_price": 79.38,
      "avg_entry_price": 80.330833,
      "side": "long",
      "exchange": "ARCA"
    },
    {
      "symbol": "XOM",
      "qty": 85.0,
      "market_value": 9926.725,
      "cost_basis": 9797.86,
      "unrealized_pl": 128.865,
      "unrealized_plpc": 0.0131523618422798,
      "current_price": 116.785,
      "avg_entry_price": 115.268941,
      "side": "long",
      "exchange": "NYSE"
    }
  ],
  "cash": -3730.98,
  "timestamp": "2025-12-02T00:17:04.557120"
}